redistimeseries/__init__.py
redistimeseries/_version.py
redistimeseries/client.py
redistimeseries-1.4.5.dist-info/LICENSE
redistimeseries-1.4.5.dist-info/WHEEL
redistimeseries-1.4.5.dist-info/METADATA
redistimeseries-1.4.5.dist-info/RECORD
