Metadata-Version: 2.1
Name: redistimeseries
Version: 1.4.5
Summary: RedisTimeSeries Python Client
License: BSD-3-Clause
Keywords: Redis TimeSeries Extension
Author: RedisLabs
Author-email: oss@redislabs.com
Requires-Python: >=3.6,<4.0
Classifier: Development Status :: 5 - Production/Stable
Classifier: Intended Audience :: Developers
Classifier: License :: OSI Approved :: BSD License
Classifier: Operating System :: OS Independent
Classifier: Programming Language :: Python
Classifier: Programming Language :: Python :: 3
Classifier: Programming Language :: Python :: 3.10
Classifier: Programming Language :: Python :: 3.6
Classifier: Programming Language :: Python :: 3.7
Classifier: Programming Language :: Python :: 3.8
Classifier: Programming Language :: Python :: 3.9
Classifier: Topic :: Database
Requires-Dist: importlib-metadata (>=4.0.1,<5.0.0)
Requires-Dist: redis (==3.5.3)
Project-URL: repository, https://github.com/RedisTimeSeries/redistimeseries-py
Project-URL: url, https://redistimeseries.io
